ros2tcp/__init__.py
ros2tcp/ROS/__init__.py
ros2tcp/ROS/bridge.py
ros2tcp/TCPsocket/TCPsocket.py
ros2tcp/TCPsocket/__init__.py
ros2tcp/plugins/__init__.py
ros2tcp/plugins/service_plugins.py
ros2tcp/plugins/srv_client.py
ros2tcp/plugins/start_server.py
ros2tcp-0.1.2.dist-info/LICENSE
ros2tcp-0.1.2.dist-info/METADATA
ros2tcp-0.1.2.dist-info/WHEEL
ros2tcp-0.1.2.dist-info/top_level.txt
ros2tcp-0.1.2.dist-info/RECORD
