Metadata-Version: 2.1
Name: ros2tcp
Version: 0.1.2
Summary: A bridge between TCP socket and DDS of ROS 2
Home-page: https://github.com/bonnybabukachappilly/ros2tcp
Author: Bonny Babu
Author-email: Bonny Babu <bonnybabukachappilly@gmail.com>
Maintainer-email: Bonny Babu <bonnybabukachappilly@gmail.com>
Project-URL: Homepage, https://github.com/bonnybabukachappilly/ros2tcp
Keywords: ROS2,Humble,socket,TCP
Classifier: Programming Language :: Python :: 3
Classifier: Programming Language :: Python :: 3.8
Classifier: License :: OSI Approved :: GNU General Public License v3 (GPLv3)
Classifier: Operating System :: Unix
Requires-Python: >=3.8
License-File: LICENSE
Provides-Extra: dev
Requires-Dist: flake8 ; extra == 'dev'
Requires-Dist: tox ; extra == 'dev'
Requires-Dist: mypy ; extra == 'dev'
Requires-Dist: check-manifest ; extra == 'dev'
Provides-Extra: test
Requires-Dist: pytest ; extra == 'test'
Requires-Dist: pytest-cov ; extra == 'test'
Requires-Dist: coverage ; extra == 'test'
